langchain_digitalocean/__init__.py
langchain_digitalocean/chat_models.py
langchain_digitalocean/document_loaders.py
langchain_digitalocean/embeddings.py
langchain_digitalocean/py.typed
langchain_digitalocean/retrievers.py
langchain_digitalocean/toolkits.py
langchain_digitalocean/tools.py
langchain_digitalocean/vectorstores.py
langchain_digitalocean-0.1.8.dist-info/LICENSE
langchain_digitalocean-0.1.8.dist-info/METADATA
langchain_digitalocean-0.1.8.dist-info/WHEEL
langchain_digitalocean-0.1.8.dist-info/RECORD
